notified_py/__init__.py
notified_py/notified.py
notified_py/platforms/__init__.py
notified_py/platforms/slack_bot.py
notified_py-1.0.4.dist-info/METADATA
notified_py-1.0.4.dist-info/WHEEL
notified_py-1.0.4.dist-info/top_level.txt
notified_py-1.0.4.dist-info/RECORD
