Metadata-Version: 2.4
Name: notified_py
Version: 1.0.4
Requires-Dist: requests==2.32.3
Requires-Dist: slack_bolt==1.23.0
Dynamic: description
Dynamic: description-content-type
Dynamic: requires-dist
